livescrape
