Metadata-Version: 1.1
Name: livescrape
Version: 0.9.3
Summary: A toolkit to build pythonic web scraper libraries
Home-page: https://github.com/ondergetekende/python-livescrape
Author: Koert van der Veer
Author-email: koert@ondergetekende.nl
License: UNKNOWN
Platform: UNKNOWN
Classifier: Intended Audience :: Developers
Classifier: Operating System :: OS Independent
Classifier: Programming Language :: Python
Classifier: Programming Language :: Python :: 3
Classifier: Programming Language :: Python :: 3.2
Classifier: Programming Language :: Python :: 3.3
Classifier: Programming Language :: Python :: 3.4
Classifier: Programming Language :: Python :: 3.5
Classifier: Programming Language :: Python :: 2.7
